{".class": "MypyFile", "_fullname": "api", "is_partial_stub_package": false, "is_stub": false, "names": {".class": "SymbolTable", "API": {".class": "SymbolTableNode", "kind": "Gdef", "node": {".class": "TypeInfo", "_promote": null, "abstract_attributes": [], "bases": ["builtins.object"], "declared_metaclass": null, "defn": {".class": "ClassDef", "fullname": "api.API", "name": "API", "type_vars": []}, "flags": [], "fullname": "api.API", "metaclass_type": null, "metadata": {}, "module_name": "api", "mro": ["api.API", "builtins.object"], "names": {".class": "SymbolTable", "get_display": {".class": "SymbolTableNode", "kind": "Mdef", "node": {".class": "Decorator", "func": {".class": "FuncDef", "arg_kinds": [0], "arg_names": ["name"], "flags": ["is_static", "is_decorated"], "fullname": "api.API.get_display", "name": "get_display", "type": {".class": "CallableType", "arg_kinds": [0], "arg_names": ["name"], "arg_types": [{".class": "AnyType", "missing_import_name": null, "source_any": null, "type_of_any": 1}], "bound_args": [], "def_extras": {"first_arg": null}, "fallback": "builtins.function", "implicit": false, "is_ellipsis_args": false, "name": "get_display of API", "ret_type": {".class": "NoneType"}, "variables": []}}, "is_overload": false, "var": {".class": "Var", "flags": ["is_initialized_in_class", "is_staticmethod", "is_ready"], "fullname": null, "name": "get_display", "type": "api.PriorGetDisplay"}}}}, "tuple_type": null, "type_vars": [], "typeddict_type": null}}, "DatasetSession": {".class": "SymbolTableNode", "cross_ref": "dataset.DatasetSession", "kind": "Gdef"}, "PriorGetDisplay": {".class": "SymbolTableNode", "kind": "Gdef", "node": {".class": "TypeInfo", "_promote": null, "abstract_attributes": [], "bases": ["builtins.object"], "declared_metaclass": null, "defn": {".class": "ClassDef", "fullname": "api.PriorGetDisplay", "name": "PriorGetDisplay", "type_vars": []}, "flags": [], "fullname": "api.PriorGetDisplay", "metaclass_type": null, "metadata": {}, "module_name": "api", "mro": ["api.PriorGetDisplay", "builtins.object"], "names": {".class": "SymbolTable", "__call__": {".class": "SymbolTableNode", "kind": "Mdef", "node": {".class": "FuncDef", "arg_kinds": [0, 2], "arg_names": ["self", "args"], "flags": [], "fullname": "api.PriorGetDisplay.__call__", "name": "__call__", "type": null}}, "__init__": {".class": "SymbolTableNode", "kind": "Mdef", "node": {".class": "FuncDef", "arg_kinds": [0, 0], "arg_names": ["self", "function"], "flags": [], "fullname": "api.PriorGetDisplay.__init__", "name": "__init__", "type": null}}}, "tuple_type": null, "type_vars": [], "typeddict_type": null}}, "__doc__": {".class": "SymbolTableNode", "kind": "Gdef", "node": {".class": "Var", "flags": ["is_ready"], "fullname": "api.__doc__", "name": "__doc__", "type": "builtins.str"}}, "__file__": {".class": "SymbolTableNode", "kind": "Gdef", "node": {".class": "Var", "flags": ["is_ready"], "fullname": "api.__file__", "name": "__file__", "type": "builtins.str"}}, "__name__": {".class": "SymbolTableNode", "kind": "Gdef", "node": {".class": "Var", "flags": ["is_ready"], "fullname": "api.__name__", "name": "__name__", "type": "builtins.str"}}, "__package__": {".class": "SymbolTableNode", "kind": "Gdef", "node": {".class": "Var", "flags": ["is_ready"], "fullname": "api.__package__", "name": "__package__", "type": "builtins.str"}}, "logging": {".class": "SymbolTableNode", "cross_ref": "logging", "kind": "Gdef"}}, "path": "./api.py"}